mc_pgzrun.py
mc_pgzrun-0.9.data/data/pgzero/data/icon.png
mc_pgzrun-0.9.data/data/pgzero/data/joypad.png
pgzero/__init__.py
pgzero/__main__.py
pgzero/actor.py
pgzero/animation.py
pgzero/builtins.py
pgzero/clock.py
pgzero/constants.py
pgzero/game.py
pgzero/keyboard.py
pgzero/loaders.py
pgzero/music.py
pgzero/pathmanager.py
pgzero/ptext.py
pgzero/rect.py
pgzero/runner.py
pgzero/screen.py
pgzero/soundfmt.py
pgzero/spellcheck.py
pgzero/tone.py
pgzero/data/icon.png
pgzero/data/joypad.png
mc_pgzrun-0.9.dist-info/METADATA
mc_pgzrun-0.9.dist-info/WHEEL
mc_pgzrun-0.9.dist-info/entry_points.txt
mc_pgzrun-0.9.dist-info/top_level.txt
mc_pgzrun-0.9.dist-info/RECORD
